License.txt
MANIFEST.in
Readme.rst
setup.cfg
setup.py
py_xliff_converter.egg-info/PKG-INFO
py_xliff_converter.egg-info/SOURCES.txt
py_xliff_converter.egg-info/dependency_links.txt
py_xliff_converter.egg-info/entry_points.txt
py_xliff_converter.egg-info/requires.txt
py_xliff_converter.egg-info/top_level.txt
xliff_converter/__init__.py
xliff_converter/html2xliff.py
xliff_converter/html_parser.py
xliff_converter/html_rebuilder.py
xliff_converter/xliff2html.py