Metadata-Version: 1.1
Name: py-xliff-converter
Version: 0.0.1
Summary: Utilities for converting rich text markup files to XLIFF format
Home-page: https://github.com/romanvm/py-xliff-converter
Author: Roman Miroshnychenko
Author-email: roman1972@gmail.com
License: MIT
Platform: UNKNOWN
Classifier: Development Status :: 4 - Beta
Classifier: Environment :: Console
Classifier: License :: OSI Approved :: MIT License
Classifier: Programming Language :: Python
Classifier: Programming Language :: Python :: 3
Classifier: Topic :: Text Processing :: Linguistic
